sharkscope/__init__.py
sharkscope/__main__.py
sharkscope/cli.py
sharkscope/server.py
sharkscope/static/favicon.svg
sharkscope/static/index.html
sharkscope/static/assets/index-Bdm-yH0W.css
sharkscope/static/assets/index-DCwI8kNv.js
sharkscope-0.1.0.dist-info/METADATA
sharkscope-0.1.0.dist-info/WHEEL
sharkscope-0.1.0.dist-info/entry_points.txt
sharkscope-0.1.0.dist-info/licenses/LICENSE
sharkscope-0.1.0.dist-info/RECORD
