Metadata-Version: 2.4
Name: sharkscope
Version: 0.1.0
Summary: Real-time network traffic visualization on a 2D map or 3D globe
Project-URL: Homepage, https://github.com/rsh3khar/sharkscope
Project-URL: Documentation, https://github.com/rsh3khar/sharkscope#readme
Project-URL: Repository, https://github.com/rsh3khar/sharkscope
Project-URL: Issues, https://github.com/rsh3khar/sharkscope/issues
Author: Raj Shekhar
License-Expression: MIT
License-File: LICENSE
Keywords: geoip,network,packet-capture,security,traffic-analysis,tshark,visualization,wireshark
Classifier: Development Status :: 4 - Beta
Classifier: Environment :: Console
Classifier: Environment :: Web Environment
Classifier: Intended Audience :: Developers
Classifier: Intended Audience :: Information Technology
Classifier: Intended Audience :: System Administrators
Classifier: License :: OSI Approved :: MIT License
Classifier: Operating System :: MacOS
Classifier: Operating System :: POSIX :: Linux
Classifier: Programming Language :: Python :: 3
Classifier: Programming Language :: Python :: 3.9
Classifier: Programming Language :: Python :: 3.10
Classifier: Programming Language :: Python :: 3.11
Classifier: Programming Language :: Python :: 3.12
Classifier: Topic :: Security
Classifier: Topic :: System :: Networking :: Monitoring
Requires-Python: >=3.9
Requires-Dist: fastapi>=0.100.0
Requires-Dist: geoip2>=4.7.0
Requires-Dist: uvicorn[standard]>=0.23.0
Requires-Dist: websockets>=11.0
Provides-Extra: dev
Requires-Dist: black>=23.0.0; extra == 'dev'
Requires-Dist: pytest>=7.0.0; extra == 'dev'
Requires-Dist: ruff>=0.1.0; extra == 'dev'
